README.rst
setup.py
fmio/__init__.py
fmio.egg-info/PKG-INFO
fmio.egg-info/SOURCES.txt
fmio.egg-info/dependency_links.txt
fmio.egg-info/entry_points.txt
fmio.egg-info/requires.txt
fmio.egg-info/top_level.txt