Metadata-Version: 1.0
Name: fmio
Version: 1.0-beta
Summary: Fast streaming I/O of numeric matrices
Home-page: http://bitbucket.org/gilesc/fmio
Author: Cory Giles
Author-email: mail@corygil.es
License: UNKNOWN
Platform: UNKNOWN
